LICENSE
MANIFEST.in
README.rst
setup.py
cchmtest/__init__.py
cchmtest/add.py
cchmtest/mult.py
cchmtest/shout.py
cchmtest/version.py
cchmtest.egg-info/PKG-INFO
cchmtest.egg-info/SOURCES.txt
cchmtest.egg-info/dependency_links.txt
cchmtest.egg-info/top_level.txt