Metadata-Version: 1.1
Name: cchmtest
Version: 1.2.4
Summary: Show how to structure a Python project.
Home-page: https://github.com/bast/somepackage
Author: Christopher Mooney
Author-email: cchmtest@example.com
License: MPL-2.0
Platform: UNKNOWN
Classifier: Development Status :: 5 - Production/Stable
Classifier: Intended Audience :: Science/Research
Classifier: Programming Language :: Python :: 2.7
Classifier: Programming Language :: Python :: 3.6
